odoo/addons/website_sale_checkout_country_vat/README.rst
odoo/addons/website_sale_checkout_country_vat/__init__.py
odoo/addons/website_sale_checkout_country_vat/__manifest__.py
odoo/addons/website_sale_checkout_country_vat/i18n/ca.po
odoo/addons/website_sale_checkout_country_vat/i18n/es.po
odoo/addons/website_sale_checkout_country_vat/i18n/fr.po
odoo/addons/website_sale_checkout_country_vat/i18n/it.po
odoo/addons/website_sale_checkout_country_vat/i18n/pt_BR.po
odoo/addons/website_sale_checkout_country_vat/i18n/website_sale_checkout_country_vat.pot
odoo/addons/website_sale_checkout_country_vat/readme/CONFIGURE.md
odoo/addons/website_sale_checkout_country_vat/readme/CONTRIBUTORS.md
odoo/addons/website_sale_checkout_country_vat/readme/DESCRIPTION.md
odoo/addons/website_sale_checkout_country_vat/readme/USAGE.md
odoo/addons/website_sale_checkout_country_vat/static/description/icon.png
odoo/addons/website_sale_checkout_country_vat/static/description/index.html
odoo/addons/website_sale_checkout_country_vat/static/src/js/dropdown.esm.js
odoo/addons/website_sale_checkout_country_vat/views/templates.xml
odoo_addon_website_sale_checkout_country_vat-18.0.1.0.0.4.dist-info/METADATA
odoo_addon_website_sale_checkout_country_vat-18.0.1.0.0.4.dist-info/WHEEL
odoo_addon_website_sale_checkout_country_vat-18.0.1.0.0.4.dist-info/top_level.txt
odoo_addon_website_sale_checkout_country_vat-18.0.1.0.0.4.dist-info/RECORD
