Metadata-Version: 2.1
Name: odoo-addon-website_sale_checkout_country_vat
Version: 18.0.1.0.0.4
Requires-Python: >=3.10
Requires-Dist: odoo-addon-website_snippet_country_dropdown==18.0.*
Requires-Dist: odoo==18.0.*
Summary: Autocomplete VAT in checkout process
Home-page: https://github.com/OCA/e-commerce
License: LGPL-3
Author: Tecnativa, Odoo Community Association (OCA)
Author-email: support@odoo-community.org
Classifier: Programming Language :: Python
Classifier: Framework :: Odoo
Classifier: Framework :: Odoo :: 18.0
Classifier: License :: OSI Approved :: GNU Lesser General Public License v3 (LGPLv3)
